rer.pubblicazioni-3.0.4-py3.10-nspkg.pth
rer/pubblicazioni/__init__.py
rer/pubblicazioni/configure.zcml
rer/pubblicazioni/indexers.py
rer/pubblicazioni/interfaces.py
rer/pubblicazioni/setuphandlers.py
rer/pubblicazioni/testing.py
rer/pubblicazioni/vocabularies.py
rer/pubblicazioni/browser/__init__.py
rer/pubblicazioni/browser/configure.zcml
rer/pubblicazioni/browser/interfaces.py
rer/pubblicazioni/browser/settings.py
rer/pubblicazioni/browser/utils_view.py
rer/pubblicazioni/browser/views.py
rer/pubblicazioni/browser/templates/pubblicazione_view.pt
rer/pubblicazioni/browser/templates/pubblicazioni_collection_view.pt
rer/pubblicazioni/locales/rer.pubblicazioni.pot
rer/pubblicazioni/locales/update.sh
rer/pubblicazioni/locales/it/LC_MESSAGES/rer.pubblicazioni.mo
rer/pubblicazioni/locales/it/LC_MESSAGES/rer.pubblicazioni.po
rer/pubblicazioni/profiles/default/browserlayer.xml
rer/pubblicazioni/profiles/default/catalog.xml
rer/pubblicazioni/profiles/default/controlpanel.xml
rer/pubblicazioni/profiles/default/metadata.xml
rer/pubblicazioni/profiles/default/registry.xml
rer/pubblicazioni/profiles/default/types.xml
rer/pubblicazioni/profiles/default/types/Collection.xml
rer/pubblicazioni/profiles/default/types/Pubblicazione.xml
rer/pubblicazioni/profiles/uninstall/browserlayer.xml
rer/pubblicazioni/profiles/uninstall/registry.xml
rer/pubblicazioni/restapi/__init__.py
rer/pubblicazioni/restapi/configure.zcml
rer/pubblicazioni/restapi/controlpanel.py
rer/pubblicazioni/tests/__init__.py
rer/pubblicazioni/tests/test_pubblicazione.py
rer/pubblicazioni/tests/test_robot.py
rer/pubblicazioni/tests/test_setup.py
rer/pubblicazioni/tests/robot/test_example.robot
rer/pubblicazioni/tests/robot/test_pubblicazione.robot
rer/pubblicazioni/upgrades/__init__.py
rer/pubblicazioni/upgrades/configure.zcml
rer/pubblicazioni/upgrades/upgrades.py
rer.pubblicazioni-3.0.4.dist-info/LICENSE.GPL
rer.pubblicazioni-3.0.4.dist-info/LICENSE.rst
rer.pubblicazioni-3.0.4.dist-info/METADATA
rer.pubblicazioni-3.0.4.dist-info/WHEEL
rer.pubblicazioni-3.0.4.dist-info/entry_points.txt
rer.pubblicazioni-3.0.4.dist-info/namespace_packages.txt
rer.pubblicazioni-3.0.4.dist-info/top_level.txt
rer.pubblicazioni-3.0.4.dist-info/RECORD
