Metadata-Version: 2.1
Name: rer.pubblicazioni
Version: 3.0.4
Summary: An add-on to manage publications for Regione Emilia Romagna.
Home-page: https://pypi.python.org/pypi/rer.pubblicazioni
Author: RedTurtle
Author-email: sviluppo@redturtle.it
License: GPL version 2
Keywords: Python Plone
Classifier: Environment :: Web Environment
Classifier: Framework :: Plone
Classifier: Framework :: Plone :: 5.0
Classifier: Programming Language :: Python
Classifier: Programming Language :: Python :: 2.7
Classifier: Operating System :: OS Independent
Classifier: License :: OSI Approved :: GNU General Public License v2 (GPLv2)
License-File: LICENSE.GPL
License-File: LICENSE.rst
Requires-Dist: setuptools
Requires-Dist: z3c.jbot
Requires-Dist: plone.volto
Provides-Extra: test
Requires-Dist: plone.app.testing ; extra == 'test'
Requires-Dist: plone.testing >=5.0.0 ; extra == 'test'
Requires-Dist: plone.app.contenttypes ; extra == 'test'
Requires-Dist: plone.app.robotframework[debug] ; extra == 'test'
